odoo/addons/l10n_th_withholding_tax_cert_form/README.rst
odoo/addons/l10n_th_withholding_tax_cert_form/__init__.py
odoo/addons/l10n_th_withholding_tax_cert_form/__manifest__.py
odoo/addons/l10n_th_withholding_tax_cert_form/data/mail_template.xml
odoo/addons/l10n_th_withholding_tax_cert_form/data/paper_format.xml
odoo/addons/l10n_th_withholding_tax_cert_form/data/withholding_tax_cert_data.xml
odoo/addons/l10n_th_withholding_tax_cert_form/i18n/l10n_th_withholding_tax_cert_form.pot
odoo/addons/l10n_th_withholding_tax_cert_form/i18n/th.po
odoo/addons/l10n_th_withholding_tax_cert_form/models/__init__.py
odoo/addons/l10n_th_withholding_tax_cert_form/models/withholding_tax_cert.py
odoo/addons/l10n_th_withholding_tax_cert_form/readme/CONTRIBUTORS.rst
odoo/addons/l10n_th_withholding_tax_cert_form/readme/DESCRIPTION.rst
odoo/addons/l10n_th_withholding_tax_cert_form/readme/USAGE.rst
odoo/addons/l10n_th_withholding_tax_cert_form/reports/withholding_tax_cert_form.xml
odoo/addons/l10n_th_withholding_tax_cert_form/reports/withholding_tax_cert_form_view.xml
odoo/addons/l10n_th_withholding_tax_cert_form/static/description/icon.png
odoo/addons/l10n_th_withholding_tax_cert_form/static/description/index.html
odoo/addons/l10n_th_withholding_tax_cert_form/static/src/img/WithholdingCert.jpg
odoo/addons/l10n_th_withholding_tax_cert_form/static/src/scss/style_report.scss
odoo/addons/l10n_th_withholding_tax_cert_form/tests/__init__.py
odoo/addons/l10n_th_withholding_tax_cert_form/tests/test_wt_cert_form.py
odoo14_addon_l10n_th_withholding_tax_cert_form-14.0.1.0.1.dist-info/METADATA
odoo14_addon_l10n_th_withholding_tax_cert_form-14.0.1.0.1.dist-info/WHEEL
odoo14_addon_l10n_th_withholding_tax_cert_form-14.0.1.0.1.dist-info/top_level.txt
odoo14_addon_l10n_th_withholding_tax_cert_form-14.0.1.0.1.dist-info/RECORD
