Metadata-Version: 2.1
Name: odoo14-addon-l10n-th-withholding-tax-cert-form
Version: 14.0.1.0.1
Summary: Thai Localization - Withholding Tax Certificate Form
Home-page: https://github.com/OCA/l10n-thailand
Author: Ecosoft, Odoo Community Association (OCA)
Author-email: support@odoo-community.org
License: AGPL-3
Platform: UNKNOWN
Classifier: Programming Language :: Python
Classifier: Framework :: Odoo
Classifier: Framework :: Odoo :: 14.0
Classifier: License :: OSI Approved :: GNU Affero General Public License v3
Requires-Python: >=3.6
Requires-Dist: odoo14-addon-l10n-th-amount-to-text
Requires-Dist: odoo14-addon-l10n-th-fonts
Requires-Dist: odoo14-addon-l10n-th-withholding-tax-cert
Requires-Dist: odoo (<14.1dev,>=14.0a)
